{
  "taskList": [
    {
      "name": "Task 1",
      "description": "Curabitur aliquet quam id dui posuere blandit. Pellentesque in",
      "id": 1
    },
    {
      "name": "Task 2",
      "description": "Curabitur aliquet quam id dui posuere blandit. Pellentesque in",
      "id": 2
    },
    {
      "name": "Task 3",
      "description": "Curabitur aliquet quam id dui posuere blandit. Pellentesque in",
      "id": 3
    },
    {
      "name": "testing",
      "description": "testing",
      "id": 4
    },
    {
      "name": "hodal data",
      "description": "dasdadasdadadad",
      "id": 5
    },
    {
      "name": "Andela Task",
      "description": "complete the react task",
      "id": 6
    },
    {
      "name": "coding",
      "description": "fffffffffffffffffffffffff",
      "id": 7
    }
  ]
}